strands_ccxt/__init__.py
strands_ccxt/_version.py
strands_ccxt/use_ccxt.py
strands_ccxt-0.1.0.dist-info/licenses/LICENSE
strands_ccxt-0.1.0.dist-info/METADATA
strands_ccxt-0.1.0.dist-info/WHEEL
strands_ccxt-0.1.0.dist-info/top_level.txt
strands_ccxt-0.1.0.dist-info/RECORD
