Metadata-Version: 2.4
Name: strands-ccxt
Version: 0.1.0
Summary: Universal CCXT tool for Strands Agents - cryptocurrency exchange integration
Author-email: Mert Ozbas <mertozbas@gmail.com>
License: Apache-2.0
Project-URL: Homepage, https://github.com/mertozbas/strands-ccxt
Project-URL: Repository, https://github.com/mertozbas/strands-ccxt
Project-URL: Issues, https://github.com/mertozbas/strands-ccxt/issues
Keywords: ccxt,ccxtpro,strands,trading,cryptocurrency,exchange,strands-agents,ai-tools
Classifier: Programming Language :: Python :: 3
Classifier: Programming Language :: Python :: 3.10
Classifier: Programming Language :: Python :: 3.11
Classifier: Programming Language :: Python :: 3.12
Classifier: Programming Language :: Python :: 3.13
Classifier: License :: OSI Approved :: Apache Software License
Classifier: Operating System :: OS Independent
Classifier: Topic :: Office/Business :: Financial :: Investment
Classifier: Topic :: Software Development :: Libraries :: Python Modules
Requires-Python: >=3.10
License-File: LICENSE
Requires-Dist: ccxt>=4.0.0
Requires-Dist: strands-agents
Provides-Extra: pro
Requires-Dist: ccxt[pro]>=4.0.0; extra == "pro"
Provides-Extra: dev
Requires-Dist: pytest>=7.0.0; extra == "dev"
Requires-Dist: pytest-asyncio>=0.21.0; extra == "dev"
Requires-Dist: python-dotenv>=1.0.0; extra == "dev"
Dynamic: license-file
